{
  "count": "https://www.courtlistener.com/api/rest/v4/positions/?count=on&person=1026",
  "next": null,
  "previous": null,
  "results": [
    {
      "resource_uri": "https://www.courtlistener.com/api/rest/v4/positions/6235/",
      "id": 6235,
      "retention_events": [],
      "person": {
        "resource_uri": "https://www.courtlistener.com/api/rest/v4/people/1026/",
        "id": 1026,
        "race": [
          "w"
        ],
        "sources": [],
        "aba_ratings": [
          {
            "resource_uri": "https://www.courtlistener.com/api/rest/v4/aba-ratings/601/",
            "id": 601,
            "person": "https://www.courtlistener.com/api/rest/v4/people/1026/",
            "date_created": "2016-04-20T08:18:06.984842-07:00",
            "date_modified": "2016-04-20T08:18:06.984864-07:00",
            "year_rated": 2007,
            "rating": "wq"
          }
        ],
        "educations": [],
        "positions": [
          "https://www.courtlistener.com/api/rest/v4/positions/6230/",
          "https://www.courtlistener.com/api/rest/v4/positions/6231/",
          "https://www.courtlistener.com/api/rest/v4/positions/6232/",
          "https://www.courtlistener.com/api/rest/v4/positions/6233/",
          "https://www.courtlistener.com/api/rest/v4/positions/6234/",
          "https://www.courtlistener.com/api/rest/v4/positions/6235/"
        ],
        "political_affiliations": [
          {
            "resource_uri": "https://www.courtlistener.com/api/rest/v4/political-affiliations/1031/",
            "id": 1031,
            "person": "https://www.courtlistener.com/api/rest/v4/people/1026/",
            "date_created": "2016-04-20T08:18:06.978707-07:00",
            "date_modified": "2016-04-20T08:18:06.978731-07:00",
            "political_party": "r",
            "source": "a",
            "date_start": "2007-01-09",
            "date_granularity_start": "%Y-%m-%d",
            "date_end": null,
            "date_granularity_end": ""
          }
        ],
        "is_alias_of": null,
        "date_created": "2016-04-20T08:18:06.948318-07:00",
        "date_modified": "2020-11-25T08:30:21.451337-08:00",
        "date_completed": null,
        "fjc_id": 3133,
        "slug": "valerie-baker-fairbank",
        "name_first": "Valerie",
        "name_middle": "Baker",
        "name_last": "Fairbank",
        "name_suffix": "",
        "date_dob": "1949-01-01",
        "date_granularity_dob": "%Y",
        "date_dod": null,
        "date_granularity_dod": "",
        "dob_city": "Minneapolis",
        "dob_state": "MN",
        "dob_country": "United States",
        "dod_city": "",
        "dod_state": "",
        "dod_country": "United States",
        "gender": "f",
        "religion": "",
        "ftm_total_received": null,
        "ftm_eid": "",
        "has_photo": true
      },
      "supervisor": null,
      "predecessor": null,
      "school": null,
      "court": null,
      "appointer": null,
      "date_created": "2016-04-20T08:18:07.089876-07:00",
      "date_modified": "2016-04-20T08:18:07.089900-07:00",
      "position_type": null,
      "job_title": "Judge",
      "sector": null,
      "organization_name": "Superior Court of California, County of Los Angeles",
      "location_city": "",
      "location_state": "",
      "date_nominated": null,
      "date_elected": null,
      "date_recess_appointment": null,
      "date_referred_to_judicial_committee": null,
      "date_judicial_committee_action": null,
      "judicial_committee_action": "",
      "date_hearing": null,
      "date_confirmation": null,
      "date_start": "1987-01-01",
      "date_granularity_start": "%Y",
      "date_termination": "2007-01-01",
      "termination_reason": "",
      "date_granularity_termination": "%Y",
      "date_retirement": null,
      "nomination_process": "",
      "vote_type": "",
      "voice_vote": null,
      "votes_yes": null,
      "votes_no": null,
      "votes_yes_percent": null,
      "votes_no_percent": null,
      "how_selected": "",
      "has_inferred_values": false
    },
    {
      "resource_uri": "https://www.courtlistener.com/api/rest/v4/positions/6234/",
      "id": 6234,
      "retention_events": [],
      "person": {
        "resource_uri": "https://www.courtlistener.com/api/rest/v4/people/1026/",
        "id": 1026,
        "race": [
          "w"
        ],
        "sources": [],
        "aba_ratings": [
          {
            "resource_uri": "https://www.courtlistener.com/api/rest/v4/aba-ratings/601/",
            "id": 601,
            "person": "https://www.courtlistener.com/api/rest/v4/people/1026/",
            "date_created": "2016-04-20T08:18:06.984842-07:00",
            "date_modified": "2016-04-20T08:18:06.984864-07:00",
            "year_rated": 2007,
            "rating": "wq"
          }
        ],
        "educations": [],
        "positions": [
          "https://www.courtlistener.com/api/rest/v4/positions/6230/",
          "https://www.courtlistener.com/api/rest/v4/positions/6231/",
          "https://www.courtlistener.com/api/rest/v4/positions/6232/",
          "https://www.courtlistener.com/api/rest/v4/positions/6233/",
          "https://www.courtlistener.com/api/rest/v4/positions/6234/",
          "https://www.courtlistener.com/api/rest/v4/positions/6235/"
        ],
        "political_affiliations": [
          {
            "resource_uri": "https://www.courtlistener.com/api/rest/v4/political-affiliations/1031/",
            "id": 1031,
            "person": "https://www.courtlistener.com/api/rest/v4/people/1026/",
            "date_created": "2016-04-20T08:18:06.978707-07:00",
            "date_modified": "2016-04-20T08:18:06.978731-07:00",
            "political_party": "r",
            "source": "a",
            "date_start": "2007-01-09",
            "date_granularity_start": "%Y-%m-%d",
            "date_end": null,
            "date_granularity_end": ""
          }
        ],
        "is_alias_of": null,
        "date_created": "2016-04-20T08:18:06.948318-07:00",
        "date_modified": "2020-11-25T08:30:21.451337-08:00",
        "date_completed": null,
        "fjc_id": 3133,
        "slug": "valerie-baker-fairbank",
        "name_first": "Valerie",
        "name_middle": "Baker",
        "name_last": "Fairbank",
        "name_suffix": "",
        "date_dob": "1949-01-01",
        "date_granularity_dob": "%Y",
        "date_dod": null,
        "date_granularity_dod": "",
        "dob_city": "Minneapolis",
        "dob_state": "MN",
        "dob_country": "United States",
        "dod_city": "",
        "dod_state": "",
        "dod_country": "United States",
        "gender": "f",
        "religion": "",
        "ftm_total_received": null,
        "ftm_eid": "",
        "has_photo": true
      },
      "supervisor": null,
      "predecessor": null,
      "school": null,
      "court": null,
      "appointer": null,
      "date_created": "2016-04-20T08:18:07.083154-07:00",
      "date_modified": "2016-04-20T08:18:07.083182-07:00",
      "position_type": null,
      "job_title": "Judge",
      "sector": null,
      "organization_name": "Los Angeles California Municipal Court",
      "location_city": "",
      "location_state": "",
      "date_nominated": null,
      "date_elected": null,
      "date_recess_appointment": null,
      "date_referred_to_judicial_committee": null,
      "date_judicial_committee_action": null,
      "judicial_committee_action": "",
      "date_hearing": null,
      "date_confirmation": null,
      "date_start": "1986-01-01",
      "date_granularity_start": "%Y",
      "date_termination": "1987-01-01",
      "termination_reason": "",
      "date_granularity_termination": "%Y",
      "date_retirement": null,
      "nomination_process": "",
      "vote_type": "",
      "voice_vote": null,
      "votes_yes": null,
      "votes_no": null,
      "votes_yes_percent": null,
      "votes_no_percent": null,
      "how_selected": "",
      "has_inferred_values": false
    },
    {
      "resource_uri": "https://www.courtlistener.com/api/rest/v4/positions/6233/",
      "id": 6233,
      "retention_events": [],
      "person": {
        "resource_uri": "https://www.courtlistener.com/api/rest/v4/people/1026/",
        "id": 1026,
        "race": [
          "w"
        ],
        "sources": [],
        "aba_ratings": [
          {
            "resource_uri": "https://www.courtlistener.com/api/rest/v4/aba-ratings/601/",
            "id": 601,
            "person": "https://www.courtlistener.com/api/rest/v4/people/1026/",
            "date_created": "2016-04-20T08:18:06.984842-07:00",
            "date_modified": "2016-04-20T08:18:06.984864-07:00",
            "year_rated": 2007,
            "rating": "wq"
          }
        ],
        "educations": [],
        "positions": [
          "https://www.courtlistener.com/api/rest/v4/positions/6230/",
          "https://www.courtlistener.com/api/rest/v4/positions/6231/",
          "https://www.courtlistener.com/api/rest/v4/positions/6232/",
          "https://www.courtlistener.com/api/rest/v4/positions/6233/",
          "https://www.courtlistener.com/api/rest/v4/positions/6234/",
          "https://www.courtlistener.com/api/rest/v4/positions/6235/"
        ],
        "political_affiliations": [
          {
            "resource_uri": "https://www.courtlistener.com/api/rest/v4/political-affiliations/1031/",
            "id": 1031,
            "person": "https://www.courtlistener.com/api/rest/v4/people/1026/",
            "date_created": "2016-04-20T08:18:06.978707-07:00",
            "date_modified": "2016-04-20T08:18:06.978731-07:00",
            "political_party": "r",
            "source": "a",
            "date_start": "2007-01-09",
            "date_granularity_start": "%Y-%m-%d",
            "date_end": null,
            "date_granularity_end": ""
          }
        ],
        "is_alias_of": null,
        "date_created": "2016-04-20T08:18:06.948318-07:00",
        "date_modified": "2020-11-25T08:30:21.451337-08:00",
        "date_completed": null,
        "fjc_id": 3133,
        "slug": "valerie-baker-fairbank",
        "name_first": "Valerie",
        "name_middle": "Baker",
        "name_last": "Fairbank",
        "name_suffix": "",
        "date_dob": "1949-01-01",
        "date_granularity_dob": "%Y",
        "date_dod": null,
        "date_granularity_dod": "",
        "dob_city": "Minneapolis",
        "dob_state": "MN",
        "dob_country": "United States",
        "dod_city": "",
        "dod_state": "",
        "dod_country": "United States",
        "gender": "f",
        "religion": "",
        "ftm_total_received": null,
        "ftm_eid": "",
        "has_photo": true
      },
      "supervisor": null,
      "predecessor": null,
      "school": null,
      "court": null,
      "appointer": null,
      "date_created": "2016-04-20T08:18:07.075142-07:00",
      "date_modified": "2016-04-20T08:18:07.075170-07:00",
      "position_type": null,
      "job_title": "Assistant U.S. attorney",
      "sector": null,
      "organization_name": "Central District of California",
      "location_city": "",
      "location_state": "",
      "date_nominated": null,
      "date_elected": null,
      "date_recess_appointment": null,
      "date_referred_to_judicial_committee": null,
      "date_judicial_committee_action": null,
      "judicial_committee_action": "",
      "date_hearing": null,
      "date_confirmation": null,
      "date_start": "1977-01-01",
      "date_granularity_start": "%Y",
      "date_termination": "1980-01-01",
      "termination_reason": "",
      "date_granularity_termination": "%Y",
      "date_retirement": null,
      "nomination_process": "",
      "vote_type": "",
      "voice_vote": null,
      "votes_yes": null,
      "votes_no": null,
      "votes_yes_percent": null,
      "votes_no_percent": null,
      "how_selected": "",
      "has_inferred_values": false
    },
    {
      "resource_uri": "https://www.courtlistener.com/api/rest/v4/positions/6232/",
      "id": 6232,
      "retention_events": [],
      "person": {
        "resource_uri": "https://www.courtlistener.com/api/rest/v4/people/1026/",
        "id": 1026,
        "race": [
          "w"
        ],
        "sources": [],
        "aba_ratings": [
          {
            "resource_uri": "https://www.courtlistener.com/api/rest/v4/aba-ratings/601/",
            "id": 601,
            "person": "https://www.courtlistener.com/api/rest/v4/people/1026/",
            "date_created": "2016-04-20T08:18:06.984842-07:00",
            "date_modified": "2016-04-20T08:18:06.984864-07:00",
            "year_rated": 2007,
            "rating": "wq"
          }
        ],
        "educations": [],
        "positions": [
          "https://www.courtlistener.com/api/rest/v4/positions/6230/",
          "https://www.courtlistener.com/api/rest/v4/positions/6231/",
          "https://www.courtlistener.com/api/rest/v4/positions/6232/",
          "https://www.courtlistener.com/api/rest/v4/positions/6233/",
          "https://www.courtlistener.com/api/rest/v4/positions/6234/",
          "https://www.courtlistener.com/api/rest/v4/positions/6235/"
        ],
        "political_affiliations": [
          {
            "resource_uri": "https://www.courtlistener.com/api/rest/v4/political-affiliations/1031/",
            "id": 1031,
            "person": "https://www.courtlistener.com/api/rest/v4/people/1026/",
            "date_created": "2016-04-20T08:18:06.978707-07:00",
            "date_modified": "2016-04-20T08:18:06.978731-07:00",
            "political_party": "r",
            "source": "a",
            "date_start": "2007-01-09",
            "date_granularity_start": "%Y-%m-%d",
            "date_end": null,
            "date_granularity_end": ""
          }
        ],
        "is_alias_of": null,
        "date_created": "2016-04-20T08:18:06.948318-07:00",
        "date_modified": "2020-11-25T08:30:21.451337-08:00",
        "date_completed": null,
        "fjc_id": 3133,
        "slug": "valerie-baker-fairbank",
        "name_first": "Valerie",
        "name_middle": "Baker",
        "name_last": "Fairbank",
        "name_suffix": "",
        "date_dob": "1949-01-01",
        "date_granularity_dob": "%Y",
        "date_dod": null,
        "date_granularity_dod": "",
        "dob_city": "Minneapolis",
        "dob_state": "MN",
        "dob_country": "United States",
        "dod_city": "",
        "dod_state": "",
        "dod_country": "United States",
        "gender": "f",
        "religion": "",
        "ftm_total_received": null,
        "ftm_eid": "",
        "has_photo": true
      },
      "supervisor": null,
      "predecessor": null,
      "school": null,
      "court": null,
      "appointer": null,
      "date_created": "2016-04-20T08:18:07.066721-07:00",
      "date_modified": "2016-04-20T08:18:07.066759-07:00",
      "position_type": null,
      "job_title": "Private practice",
      "sector": null,
      "organization_name": "",
      "location_city": "Los Angeles",
      "location_state": "CA",
      "date_nominated": null,
      "date_elected": null,
      "date_recess_appointment": null,
      "date_referred_to_judicial_committee": null,
      "date_judicial_committee_action": null,
      "judicial_committee_action": "",
      "date_hearing": null,
      "date_confirmation": null,
      "date_start": "1980-01-01",
      "date_granularity_start": "%Y",
      "date_termination": "1986-01-01",
      "termination_reason": "",
      "date_granularity_termination": "%Y",
      "date_retirement": null,
      "nomination_process": "",
      "vote_type": "",
      "voice_vote": null,
      "votes_yes": null,
      "votes_no": null,
      "votes_yes_percent": null,
      "votes_no_percent": null,
      "how_selected": "",
      "has_inferred_values": false
    },
    {
      "resource_uri": "https://www.courtlistener.com/api/rest/v4/positions/6231/",
      "id": 6231,
      "retention_events": [],
      "person": {
        "resource_uri": "https://www.courtlistener.com/api/rest/v4/people/1026/",
        "id": 1026,
        "race": [
          "w"
        ],
        "sources": [],
        "aba_ratings": [
          {
            "resource_uri": "https://www.courtlistener.com/api/rest/v4/aba-ratings/601/",
            "id": 601,
            "person": "https://www.courtlistener.com/api/rest/v4/people/1026/",
            "date_created": "2016-04-20T08:18:06.984842-07:00",
            "date_modified": "2016-04-20T08:18:06.984864-07:00",
            "year_rated": 2007,
            "rating": "wq"
          }
        ],
        "educations": [],
        "positions": [
          "https://www.courtlistener.com/api/rest/v4/positions/6230/",
          "https://www.courtlistener.com/api/rest/v4/positions/6231/",
          "https://www.courtlistener.com/api/rest/v4/positions/6232/",
          "https://www.courtlistener.com/api/rest/v4/positions/6233/",
          "https://www.courtlistener.com/api/rest/v4/positions/6234/",
          "https://www.courtlistener.com/api/rest/v4/positions/6235/"
        ],
        "political_affiliations": [
          {
            "resource_uri": "https://www.courtlistener.com/api/rest/v4/political-affiliations/1031/",
            "id": 1031,
            "person": "https://www.courtlistener.com/api/rest/v4/people/1026/",
            "date_created": "2016-04-20T08:18:06.978707-07:00",
            "date_modified": "2016-04-20T08:18:06.978731-07:00",
            "political_party": "r",
            "source": "a",
            "date_start": "2007-01-09",
            "date_granularity_start": "%Y-%m-%d",
            "date_end": null,
            "date_granularity_end": ""
          }
        ],
        "is_alias_of": null,
        "date_created": "2016-04-20T08:18:06.948318-07:00",
        "date_modified": "2020-11-25T08:30:21.451337-08:00",
        "date_completed": null,
        "fjc_id": 3133,
        "slug": "valerie-baker-fairbank",
        "name_first": "Valerie",
        "name_middle": "Baker",
        "name_last": "Fairbank",
        "name_suffix": "",
        "date_dob": "1949-01-01",
        "date_granularity_dob": "%Y",
        "date_dod": null,
        "date_granularity_dod": "",
        "dob_city": "Minneapolis",
        "dob_state": "MN",
        "dob_country": "United States",
        "dod_city": "",
        "dod_state": "",
        "dod_country": "United States",
        "gender": "f",
        "religion": "",
        "ftm_total_received": null,
        "ftm_eid": "",
        "has_photo": true
      },
      "supervisor": null,
      "predecessor": null,
      "school": null,
      "court": null,
      "appointer": null,
      "date_created": "2016-04-20T08:18:07.057248-07:00",
      "date_modified": "2016-04-20T08:18:07.057276-07:00",
      "position_type": null,
      "job_title": "Private practice",
      "sector": null,
      "organization_name": "",
      "location_city": "Los Angeles",
      "location_state": "CA",
      "date_nominated": null,
      "date_elected": null,
      "date_recess_appointment": null,
      "date_referred_to_judicial_committee": null,
      "date_judicial_committee_action": null,
      "judicial_committee_action": "",
      "date_hearing": null,
      "date_confirmation": null,
      "date_start": "1975-01-01",
      "date_granularity_start": "%Y",
      "date_termination": "1977-01-01",
      "termination_reason": "",
      "date_granularity_termination": "%Y",
      "date_retirement": null,
      "nomination_process": "",
      "vote_type": "",
      "voice_vote": null,
      "votes_yes": null,
      "votes_no": null,
      "votes_yes_percent": null,
      "votes_no_percent": null,
      "how_selected": "",
      "has_inferred_values": false
    },
    {
      "resource_uri": "https://www.courtlistener.com/api/rest/v4/positions/6230/",
      "id": 6230,
      "retention_events": [],
      "person": {
        "resource_uri": "https://www.courtlistener.com/api/rest/v4/people/1026/",
        "id": 1026,
        "race": [
          "w"
        ],
        "sources": [],
        "aba_ratings": [
          {
            "resource_uri": "https://www.courtlistener.com/api/rest/v4/aba-ratings/601/",
            "id": 601,
            "person": "https://www.courtlistener.com/api/rest/v4/people/1026/",
            "date_created": "2016-04-20T08:18:06.984842-07:00",
            "date_modified": "2016-04-20T08:18:06.984864-07:00",
            "year_rated": 2007,
            "rating": "wq"
          }
        ],
        "educations": [],
        "positions": [
          "https://www.courtlistener.com/api/rest/v4/positions/6230/",
          "https://www.courtlistener.com/api/rest/v4/positions/6231/",
          "https://www.courtlistener.com/api/rest/v4/positions/6232/",
          "https://www.courtlistener.com/api/rest/v4/positions/6233/",
          "https://www.courtlistener.com/api/rest/v4/positions/6234/",
          "https://www.courtlistener.com/api/rest/v4/positions/6235/"
        ],
        "political_affiliations": [
          {
            "resource_uri": "https://www.courtlistener.com/api/rest/v4/political-affiliations/1031/",
            "id": 1031,
            "person": "https://www.courtlistener.com/api/rest/v4/people/1026/",
            "date_created": "2016-04-20T08:18:06.978707-07:00",
            "date_modified": "2016-04-20T08:18:06.978731-07:00",
            "political_party": "r",
            "source": "a",
            "date_start": "2007-01-09",
            "date_granularity_start": "%Y-%m-%d",
            "date_end": null,
            "date_granularity_end": ""
          }
        ],
        "is_alias_of": null,
        "date_created": "2016-04-20T08:18:06.948318-07:00",
        "date_modified": "2020-11-25T08:30:21.451337-08:00",
        "date_completed": null,
        "fjc_id": 3133,
        "slug": "valerie-baker-fairbank",
        "name_first": "Valerie",
        "name_middle": "Baker",
        "name_last": "Fairbank",
        "name_suffix": "",
        "date_dob": "1949-01-01",
        "date_granularity_dob": "%Y",
        "date_dod": null,
        "date_granularity_dod": "",
        "dob_city": "Minneapolis",
        "dob_state": "MN",
        "dob_country": "United States",
        "dod_city": "",
        "dod_state": "",
        "dod_country": "United States",
        "gender": "f",
        "religion": "",
        "ftm_total_received": null,
        "ftm_eid": "",
        "has_photo": true
      },
      "supervisor": null,
      "predecessor": null,
      "school": null,
      "court": {
        "resource_uri": "https://www.courtlistener.com/api/rest/v4/courts/cacd/",
        "id": "cacd",
        "pacer_court_id": 31,
        "pacer_has_rss_feed": true,
        "pacer_rss_entry_types": "all",
        "date_last_pacer_contact": null,
        "fjc_court_id": "73",
        "date_modified": "2023-10-02T18:23:43.723245-07:00",
        "in_use": true,
        "has_opinion_scraper": false,
        "has_oral_argument_scraper": false,
        "position": 205.05,
        "citation_string": "C.D. Cal.",
        "short_name": "C.D. California",
        "full_name": "District Court, C.D. California",
        "url": "http://www.cacd.uscourts.gov/",
        "start_date": null,
        "end_date": null,
        "jurisdiction": "FD",
        "parent_court": "https://www.courtlistener.com/api/rest/v4/courts/usdistct/",
        "appeals_to": []
      },
      "appointer": "https://www.courtlistener.com/api/rest/v4/positions/43/",
      "date_created": "2016-04-20T08:18:06.973058-07:00",
      "date_modified": "2016-04-20T08:18:06.973081-07:00",
      "position_type": "jud",
      "job_title": "",
      "sector": null,
      "organization_name": null,
      "location_city": "",
      "location_state": "",
      "date_nominated": "2007-01-09",
      "date_elected": null,
      "date_recess_appointment": null,
      "date_referred_to_judicial_committee": "2007-01-09",
      "date_judicial_committee_action": "2007-01-25",
      "judicial_committee_action": "",
      "date_hearing": "2006-08-01",
      "date_confirmation": "2007-02-01",
      "date_start": "2007-02-16",
      "date_granularity_start": "%Y-%m-%d",
      "date_termination": null,
      "termination_reason": "",
      "date_granularity_termination": "",
      "date_retirement": "2012-03-01",
      "nomination_process": "",
      "vote_type": "s",
      "voice_vote": true,
      "votes_yes": null,
      "votes_no": null,
      "votes_yes_percent": null,
      "votes_no_percent": null,
      "how_selected": "a_pres",
      "has_inferred_values": false
    }
  ]
}